{
  "name": "dummy",
  "age": 25,
  "gender": "male",
  "address": "India",
  "medical_history": {
    "chronic_illnesses": ["Type 2 Diabetes", "Hypertension"],
    "past_surgeries": ["Appendectomy - 2015"],
    "allergies": ["Penicillin", "Peanuts"],
    "medications": ["Metformin", "Lisinopril"],
    "family_history": ["Father had heart disease", "Mother had diabetes"],
    "lifestyle": {
      "smoking": false,
      "alcohol": "Occasionally",
      "exercise": "3 times a week"
    },
    "immunizations": ["COVID-19 (2021)", "Tetanus (2019)"],
    "previous_hospitalizations": ["Pneumonia - 2018"],
    "mental_health": ["Mild Anxiety"]
  },
  "user": "http://127.0.0.1:8000/users/1/"
}

{
    "patient": "http://127.0.0.1:8000/patients/1/",
    "doctor_name": "Dr. Smith",
    "diagnosis": "Mild Angina (Chest Pain due to Reduced Blood Flow to the Heart)",
    "prescribed_medications": ["Aspirin 75mg", "Nitroglycerin"],
    "lab_tests": ["ECG", "Blood Pressure Test"],
    "visit_date": "2025-02-06",
    "next_visit": "2025-02-20"
}
  